vnpy_arctic/__init__.py
vnpy_arctic/arctic_database.py
vnpy_arctic-1.0.4.dist-info/LICENSE
vnpy_arctic-1.0.4.dist-info/METADATA
vnpy_arctic-1.0.4.dist-info/WHEEL
vnpy_arctic-1.0.4.dist-info/top_level.txt
vnpy_arctic-1.0.4.dist-info/RECORD
