Metadata-Version: 2.1
Name: vnpy-arctic
Version: 1.0.4
Summary: arctic database manager for VeighNa quant trading framework.
Home-page: https://www.vnpy.com
Author: Xiaoyou Chen
Author-email: xiaoyou.chen@mail.vnpy.com
License: MIT
Keywords: quant,quantitative,investment,trading,algotrading
Platform: UNKNOWN
Classifier: Development Status :: 5 - Production/Stable
Classifier: Operating System :: OS Independent
Classifier: Programming Language :: Python :: 3
Classifier: Programming Language :: Python :: 3.7
Classifier: Programming Language :: Python :: 3.8
Classifier: Topic :: Office/Business :: Financial :: Investment
Classifier: Programming Language :: Python :: Implementation :: CPython
Classifier: License :: OSI Approved :: MIT License
Classifier: Natural Language :: Chinese (Simplified)
License-File: LICENSE
Requires-Dist: arctic
Requires-Dist: pandas (<=1.0.3)
